ircpy/__init__.py
ircpy/irc.py
ircpy-1.1.3.dist-info/LICENSE
ircpy-1.1.3.dist-info/METADATA
ircpy-1.1.3.dist-info/WHEEL
ircpy-1.1.3.dist-info/top_level.txt
ircpy-1.1.3.dist-info/RECORD
