Metadata-Version: 2.1
Name: ircpy
Version: 1.1.3
Summary: IRC library for Python3
Author-email: User0 <user0thenyancat@proton.me>
Project-URL: Homepage, https://github.com/user0-07161/irc.py
Project-URL: Issues, https://github.com/user0-07161/irc.py/issues
Classifier: Programming Language :: Python :: 3
Classifier: Operating System :: OS Independent
Requires-Python: >=3.8
License-File: LICENSE
Requires-Dist: telnetlib3
